vsai/__init__.py
vsai/bot.py
vsai-1.4.1.dist-info/METADATA
vsai-1.4.1.dist-info/WHEEL
vsai-1.4.1.dist-info/entry_points.txt
vsai-1.4.1.dist-info/top_level.txt
vsai-1.4.1.dist-info/RECORD
